kamalfirstpackage/__init__.py
kamalfirstpackage/cli.py
kamalfirstpackage/core.py
kamalfirstpackage/core2.py
kamalfirstpackage-0.1.3.dist-info/LICENSE
kamalfirstpackage-0.1.3.dist-info/METADATA
kamalfirstpackage-0.1.3.dist-info/WHEEL
kamalfirstpackage-0.1.3.dist-info/entry_points.txt
kamalfirstpackage-0.1.3.dist-info/top_level.txt
kamalfirstpackage-0.1.3.dist-info/RECORD
